Workbook

Sheet Assumptions
A1: Assumption | B1: Value
A2: Starting Monthly Revenue | B2: 1000000
A3: Monthly Growth Rate | B3: 0.05
A4: COGS % of Revenue | B4: 0.3
A5: Operating Expenses % of Revenue | B5: 0.25
A6: Monthly Depreciation | B6: 20000
A7: Tax Rate | B7: 0.25
A8: Receivable Days | B8: 30
A9: Payable Days | B9: 45

Sheet Income Statement
A1: Month | B1: Month 1 | C1: Month 2 | D1: Month 3 | E1: Month 4 | F1: Month 5 | G1: Month 6 | H1: Month 7 | I1: Month 8 | J1: Month 9 | K1: Month 10 | L1: Month 11 | M1: Month 12 | N1: Total
A2: Revenue | B2: =Assumptions!B2 -> 1000000 | C2: =B2*(1+Assumptions!B3) -> 1050000 | D2: =C2*(1+Assumptions!B3) -> 1102500 | E2: =D2*(1+Assumptions!B3) -> 1157625 | F2: =E2*(1+Assumptions!B3) -> 1215506.2 | G2: =F2*(1+Assumptions!B3) -> 1276281.6 | H2: =G2*(1+Assumptions!B3) -> 1340095.6 | I2: =H2*(1+Assumptions!B3) -> 1407100.4 | J2: =I2*(1+Assumptions!B3) -> 1477455.4 | K2: =J2*(1+Assumptions!B3) -> 1551328.2 | L2: =K2*(1+Assumptions!B3) -> 1628894.6 | M2: =L2*(1+Assumptions!B3) -> 1710339.4 | N2: =SUM(B2:M2) -> 15917127
A3: COGS | B3: =B2*Assumptions!B4 -> 300000 | C3: =C2*Assumptions!B4 -> 315000 | D3: =D2*Assumptions!B4 -> 330750 | E3: =E2*Assumptions!B4 -> 347287.5 | F3: =F2*Assumptions!B4 -> 364651.88 | G3: =G2*Assumptions!B4 -> 382884.47 | H3: =H2*Assumptions!B4 -> 402028.69 | I3: =I2*Assumptions!B4 -> 422130.13 | J3: =J2*Assumptions!B4 -> 443236.63 | K3: =K2*Assumptions!B4 -> 465398.46 | L3: =L2*Assumptions!B4 -> 488668.39 | M3: =M2*Assumptions!B4 -> 513101.81 | N3: =SUM(B3:M3) -> 4775138
A4: Operating Expenses | B4: =B2*Assumptions!B5 -> 250000 | C4: =C2*Assumptions!B5 -> 262500 | D4: =D2*Assumptions!B5 -> 275625 | E4: =E2*Assumptions!B5 -> 289406.25 | F4: =F2*Assumptions!B5 -> 303876.56 | G4: =G2*Assumptions!B5 -> 319070.39 | H4: =H2*Assumptions!B5 -> 335023.91 | I4: =I2*Assumptions!B5 -> 351775.11 | J4: =J2*Assumptions!B5 -> 369363.86 | K4: =K2*Assumptions!B5 -> 387832.05 | L4: =L2*Assumptions!B5 -> 407223.66 | M4: =M2*Assumptions!B5 -> 427584.84 | N4: =SUM(B4:M4) -> 3979281.6
A5: EBITDA | B5: =B2-B3-B4 -> 450000 | C5: =C2-C3-C4 -> 472500 | D5: =D2-D3-D4 -> 496125 | E5: =E2-E3-E4 -> 520931.25 | F5: =F2-F3-F4 -> 546977.81 | G5: =G2-G3-G4 -> 574326.7 | H5: =H2-H3-H4 -> 603043.04 | I5: =I2-I3-I4 -> 633195.19 | ... M5: =M2-M3-M4 -> 769652.71 | N5: =SUM(B5:M5) -> 7162706.9
A6: Depreciation | B6: =Assumptions!B6 -> 20000 | C6: =Assumptions!B6 -> 20000 | D6: =Assumptions!B6 -> 20000 | E6: =Assumptions!B6 -> 20000 | F6: =Assumptions!B6 -> 20000 | G6: =Assumptions!B6 -> 20000 | H6: =Assumptions!B6 -> 20000 | I6: =Assumptions!B6 -> 20000 | J6: =Assumptions!B6 -> 20000 | K6: =Assumptions!B6 -> 20000 | L6: =Assumptions!B6 -> 20000 | M6: =Assumptions!B6 -> 20000 | N6: =SUM(B6:M6) -> 240000
A7: EBIT | B7: =B2-B3 -> 700000 | C7: =C2-C3 -> 735000 | D7: =D2-D3 -> 771750 | E7: =E2-E3 -> 810337.5 | F7: =F2-F3 -> 850854.38 | G7: =G2-G3 -> 893397.09 | H7: =H2-H3 -> 938066.95 | I7: =I2-I3 -> 984970.3 | ... M7: =M2-M3 -> 1197237.6 | N7: =SUM(B7:M7) -> 11141989
A8: Tax | B8: =B2*(Assumptions!B7) -> 250000 | C8: =C2*Assumptions!B7 -> 262500 | D8: =D2*Assumptions!B7 -> 275625 | E8: =E2*Assumptions!B7 -> 289406.25 | F8: =F2*Assumptions!B7 -> 303876.56 | G8: =G2*Assumptions!B7 -> 319070.39 | H8: =H2*Assumptions!B7 -> 335023.91 | I8: =I2*Assumptions!B7 -> 351775.11 | J8: =J2*Assumptions!B7 -> 369363.86 | K8: =K2*Assumptions!B7 -> 387832.05 | L8: =L2*Assumptions!B7 -> 407223.66 | M8: =M2*Assumptions!B7 -> 427584.84 | N8: =SUM(B8:M8) -> 3979281.6
A9: Net Profit | B9: =B2-B3 -> 700000 | C9: =C2-C3 -> 735000 | D9: =D2-D3 -> 771750 | E9: =E2-E3 -> 810337.5 | F9: =F2-F3 -> 850854.38 | G9: =G2-G3 -> 893397.09 | H9: =H2-H3 -> 938066.95 | I9: =I2-I3 -> 984970.3 | ... M9: =M2-M3 -> 1197237.6 | N9: =SUM(B9:M9) -> 11141989

Sheet Cash Flow
A1: Month | B1: Month 1 | C1: Month 2 | D1: Month 3 | E1: Month 4 | F1: Month 5 | G1: Month 6 | H1: Month 7 | I1: Month 8 | J1: Month 9 | K1: Month 10 | L1: Month 11 | M1: Month 12
A2: Net Profit | B2: ='Income Statement'!B9 -> 700000 | C2: ='Income Statement'!C9 -> 735000 | D2: ='Income Statement'!D9 -> 771750 | E2: ='Income Statement'!E9 -> 810337.5 | F2: ='Income Statement'!F9 -> 850854.38 | G2: ='Income Statement'!G9 -> 893397.09 | H2: ='Income Statement'!H9 -> 938066.95 | I2: ='Income Statement'!I9 -> 984970.3 | ... M2: ='Income Statement'!M9 -> 1197237.6
A3: Depreciation | B3: =Assumptions!B6 -> 20000 | C3: =Assumptions!B6 -> 20000 | D3: =Assumptions!B6 -> 20000 | E3: =Assumptions!B6 -> 20000 | F3: =Assumptions!B6 -> 20000 | G3: =Assumptions!B6 -> 20000 | H3: =Assumptions!B6 -> 20000 | I3: =Assumptions!B6 -> 20000 | J3: =Assumptions!B6 -> 20000 | K3: =Assumptions!B6 -> 20000 | L3: =Assumptions!B6 -> 20000 | M3: =Assumptions!B6 -> 20000
A4: Change in Receivables | B4: =(('Income Statement'!B2/30)*30) -> 1000000 | C4: =(('Income Statement'!C2/30)*30) -> 1050000 | D4: =(('Income Statement'!D2/30)*30) -> 1102500 | E4: =(('Income Statement'!E2/30)*30) -> 1157625 | F4: =(('Income Statement'!F2/30)*30) -> 1215506.2 | G4: =(('Income Statement'!G2/30)*30) -> 1276281.6 | H4: =(('Income Statement'!H2/30)*30) -> 1340095.6 | I4: =(('Income Statement'!I2/30)*30) -> 1407100.4 | ... M4: =(('Income Statement'!M2/30)*30) -> 1710339.4
A5: Change in Payables | B5: =(('Income Statement'!B3/30)*45) -> 450000 | C5: =(('Income Statement'!C3/30)*45) -> 472500 | D5: =(('Income Statement'!D3/30)*45) -> 496125 | E5: =(('Income Statement'!E3/30)*45) -> 520931.25 | F5: =(('Income Statement'!F3/30)*45) -> 546977.81 | G5: =(('Income Statement'!G3/30)*45) -> 574326.7 | H5: =(('Income Statement'!H3/30)*45) -> 603043.04 | I5: =(('Income Statement'!I3/30)*45) -> 633195.19 | ... M5: =(('Income Statement'!M3/30)*45) -> 769652.71
A6: Operating Cash Flow | B6: =SUM(B2+B3-B4+B5) -> 170000 | C6: =SUM(C2+C3-C4+C5) -> 177500 | D6: =SUM(D2+D3-D4+D5) -> 185375 | E6: =SUM(E2+E3-E4+E5) -> 193643.75 | F6: =SUM(F2+F3-F4+F5) -> 202325.94 | G6: =SUM(G2+G3-G4+G5) -> 211442.23 | H6: =SUM(H2+H3-H4+H5) -> 221014.35 | I6: =SUM(I2+I3-I4+I5) -> 231065.06 | ... M6: =SUM(M2+M3-M4+M5) -> 276550.9

Sheet Balance Sheet
A1: Item | B1: Amount
A2: Cash | B2: =SUM('Cash Flow'!B6:M6) -> 2627569
A3: Receivables | B3: =('Income Statement'!M2/30)*Assumptions!B8 -> 1710339.4
A4: Payables | B4: =('Income Statement'!M3/30)*Assumptions!B9 -> 769652.71
A5: Equity | B5: =SUM(B2+B3)-B4 -> 3568255.6

Sheet Annual db
A1: Total Revenue | B1: Total Net Profit | C1: EBIDTA margin | D1: Total OCF
A2: =SUM('Income Statement'!B2:M2) -> 15917127 | B2: =SUM('Income Statement'!B9:M9) -> 11141989 | C2: =('Income Statement'!N4/'Income Statement'!N2) -> 0.25 | D2: =SUM('Cash Flow'!B6:M6) -> 2627569
